{
    "title": "Citadel Storm! - Into the Breach - Massive Siege Battles #1",
    "description": "Welcome to a new series that is going to be focused around massive siege battles for all Total War Titles.  So when you see a new video for this series you know what to expect..A Massive Siege battle.  This one is a 4v3 Online battle in medieval 2 Total War.  The 4 attackers are attacking a Citadel..enjoy :D\n_\nVisit my Website & Podcast!\n\nThanks to this awesome community I built a website for Total War fans, gamers, and history nerds.  It has blog posts, a Podcast, and a forum.  \n\nTotal War Tavern (Website): http:\/\/totalwartavern.com\/\n\nThe Round Table (Podcast-itunes): https:\/\/itunes.apple.com\/us\/podcast\/round-table-total-war-gaming\/id1012071205?mt=2\n\n*Be sure to give the podcast 5 Stars :D\n-------------------------------------------------------------------------------------------------------------\n\nHow to send me Battle Replays!\n\nThis video will show you how to send me battle replays :D https:\/\/www.youtube.com\/watch?v=7nG3uZoDkCU\n-------------------------------------------------------------------------------------------------------------\n\nHow to play Medieval 2 Total War & Rome Total War Online!\n\nGamespy Servers are down, but there is still hope.  Thanks to CA and steam you can still play the game online\n\nHow to play Online: https:\/\/www.youtube.com\/watch?v=YGfItCMitPg\n-------------------------------------------------------------------------------------------------------------\n\nWhy do I block out the Mini-Map with annotations for Sub battle replays?\n\nI block it out because the Mini-Map gives away who sent in the battle replay.  And in most cases whoever sends in the battle replay wins the battle.  So I block it to keep it a surprise :D  \n\n_\n\nConnect With me!\n\nEmail: pixelatedapollo@gmail.com\nTwitter: https:\/\/twitter.com\/PixelatedApollo\nSteam Group:  http:\/\/steamcommunity.com\/groups\/apollosknights\nTwitch: http:\/\/www.twitch.tv\/pixelatedapollo\nTeamSpeak: thewarcamp.vortexservers.com:10124",
    "referenceId": "L3WAjiQWqpA",
    "date_created": "1447784811",
    "date_modified": "1507771999",
    "tags": "",
    "sourceId": "4",
    "status": "approved",
    "visibility": "1",
    "VV_VI": null,
    "engagement_score": null,
    "conversion_score": null,
    "CVV_VI": null,
    "id": "117407169",
    "loginId": "1759035",
    "entityType": "1",
    "titleTextEncoded": "Citadel-Storm-Into-the-Breach-Massive-Siege-Battles-1",
    "category": "",
    "tvp_profiles": [
        "25",
        "11",
        "18"
    ],
    "tvp_profiles_manual": "",
    "tvp_profiles_maxscore": 2363.7737,
    "VIDEO_LENGTH": "LONG",
    "duration": 3073,
    "settings": "",
    "asset": {
        "type": "youtube",
        "thumbnailUrl": "https:\/\/i.ytimg.com\/vi\/L3WAjiQWqpA\/maxresdefault.jpg",
        "uploadDate": 1447784811,
        "videoId": "L3WAjiQWqpA",
        "title": "Citadel Storm! - Into the Breach - Massive Siege Battles #1",
        "description": "Welcome to a new series that is going to be focused around massive siege battles for all Total War Titles.  So when you see a new video for this series you know what to expect..A Massive Siege battle.  This one is a 4v3 Online battle in medieval 2 Total War.  The 4 attackers are attacking a Citadel..enjoy :D\n_\nVisit my Website & Podcast!\n\nThanks to this awesome community I built a website for Total War fans, gamers, and history nerds.  It has blog posts, a Podcast, and a forum.  \n\nTotal War Tavern (Website): http:\/\/totalwartavern.com\/\n\nThe Round Table (Podcast-itunes): https:\/\/itunes.apple.com\/us\/podcast\/round-table-total-war-gaming\/id1012071205?mt=2\n\n*Be sure to give the podcast 5 Stars :D\n-------------------------------------------------------------------------------------------------------------\n\nHow to send me Battle Replays!\n\nThis video will show you how to send me battle replays :D https:\/\/www.youtube.com\/watch?v=7nG3uZoDkCU\n-------------------------------------------------------------------------------------------------------------\n\nHow to play Medieval 2 Total War & Rome Total War Online!\n\nGamespy Servers are down, but there is still hope.  Thanks to CA and steam you can still play the game online\n\nHow to play Online: https:\/\/www.youtube.com\/watch?v=YGfItCMitPg\n-------------------------------------------------------------------------------------------------------------\n\nWhy do I block out the Mini-Map with annotations for Sub battle replays?\n\nI block it out because the Mini-Map gives away who sent in the battle replay.  And in most cases whoever sends in the battle replay wins the battle.  So I block it to keep it a surprise :D  \n\n_\n\nConnect With me!\n\nEmail: pixelatedapollo@gmail.com\nTwitter: https:\/\/twitter.com\/PixelatedApollo\nSteam Group:  http:\/\/steamcommunity.com\/groups\/apollosknights\nTwitch: http:\/\/www.twitch.tv\/pixelatedapollo\nTeamSpeak: thewarcamp.vortexservers.com:10124",
        "author": "Pixelated Apollo",
        "mediaDuration": 3073,
        "prettyDuration": "00:51:13",
        "views": "36235"
    },
    "transcripts": "",
    "metrics_statistics": ""
}